Results/scripts/2d.py
Results/scripts/bubble.py
Results/scripts/bubble2.py
Results/scripts/bubbleCodeCarbon.py
Results/scripts/bubble_pyJoules.py
Results/scripts/carbon_intViz.py
Results/scripts/idlePyjoules.py
Results/scripts/insertion.py
Results/scripts/insertionCodeCarbon.py
Results/scripts/lessHits.py
Results/scripts/merge.py
Results/scripts/mergeCodeCarbon.py
Results/scripts/moreHits.py
Results/scripts/quick.py
Results/scripts/quickCodeCarbon.py
Results/scripts/selection.py
Results/scripts/selectionCodeCarbon.py
Results/scripts/sort.py
Results/sorting/bubble.py
Results/sorting/bubble_sort.py
Results/sorting/dataVizSort.py
Results/sorting/insertion_sort.py
Results/sorting/merge_sort.py
Results/sorting/quick_sort.py
Results/sorting/selection_sort.py
build/lib/Results/scripts/2d.py
build/lib/Results/scripts/bubble.py
build/lib/Results/scripts/bubble2.py
build/lib/Results/scripts/bubbleCodeCarbon.py
build/lib/Results/scripts/bubble_pyJoules.py
build/lib/Results/scripts/carbon_intViz.py
build/lib/Results/scripts/idlePyjoules.py
build/lib/Results/scripts/insertion.py
build/lib/Results/scripts/insertionCodeCarbon.py
build/lib/Results/scripts/lessHits.py
build/lib/Results/scripts/merge.py
build/lib/Results/scripts/mergeCodeCarbon.py
build/lib/Results/scripts/moreHits.py
build/lib/Results/scripts/quick.py
build/lib/Results/scripts/quickCodeCarbon.py
build/lib/Results/scripts/selection.py
build/lib/Results/scripts/selectionCodeCarbon.py
build/lib/Results/scripts/sort.py
build/lib/Results/sorting/bubble.py
build/lib/Results/sorting/bubble_sort.py
build/lib/Results/sorting/dataVizSort.py
build/lib/Results/sorting/insertion_sort.py
build/lib/Results/sorting/merge_sort.py
build/lib/Results/sorting/quick_sort.py
build/lib/Results/sorting/selection_sort.py
build/lib/build/lib/Results/scripts/2d.py
build/lib/build/lib/Results/scripts/bubble.py
build/lib/build/lib/Results/scripts/bubble2.py
build/lib/build/lib/Results/scripts/bubbleCodeCarbon.py
traceCarbon-0.0.2.dist-info/LICENSE
traceCarbon-0.0.2.dist-info/METADATA
traceCarbon-0.0.2.dist-info/WHEEL
traceCarbon-0.0.2.dist-info/entry_points.txt
traceCarbon-0.0.2.dist-info/top_level.txt
traceCarbon-0.0.2.dist-info/RECORD
