Metadata-Version: 2.1
Name: traceCarbon
Version: 0.0.2
Requires-Python: >=3.10
License-File: LICENSE
Requires-Dist: requests
Requires-Dist: pyJoules
Requires-Dist: click
Requires-Dist: pynvml
Requires-Dist: geocoder
